MANIFEST.in
setup.py
bin/bluerun
bin/qconvert
bin/taskrun
etc/blueprint.cfg
etc/env_wrapper.sh
etc/postrun.sh
etc/prerun.sh
lib/blueprint/__init__.py
lib/blueprint/app.py
lib/blueprint/archive.py
lib/blueprint/conf.py
lib/blueprint/exception.py
lib/blueprint/io.py
lib/blueprint/job.py
lib/blueprint/layer.py
lib/blueprint/backend/__init__.py
lib/blueprint/backend/plowrun.py
lib/blueprint/backend/test.py
lib/blueprint/modules/__init__.py
lib/blueprint/modules/blender.py
lib/blueprint/modules/iconvert.py
lib/blueprint/modules/maya.py
lib/blueprint/modules/nuke.py
lib/blueprint/modules/shell.py
lib/blueprint/modules/setup/blender_setup.py
lib/blueprint/plugins/__init__.py
lib/blueprint/plugins/plow_outputs.py
lib/blueprint/plugins/test_plugin.py
lib/plow_blueprint.egg-info/PKG-INFO
lib/plow_blueprint.egg-info/SOURCES.txt
lib/plow_blueprint.egg-info/dependency_links.txt
lib/plow_blueprint.egg-info/not-zip-safe
lib/plow_blueprint.egg-info/top_level.txt
tests/__init__.py
tests/common.py
tests/setup.py
tests/test_all.py
tests/test_app.py
tests/test_archive.py
tests/test_conf.py
tests/test_job.py
tests/test_layer.py
tests/test_module_blender.py
tests/test_module_maya.py
tests/test_taskrun.py