Metadata-Version: 1.0
Name: plow-blueprint
Version: 0.1.3
Summary: A Python library for distributing computing using the Plow Render Farm
Home-page: https://github.com/sqlboy/blueprint
Author: Matt Chambers
Author-email: yougotrooted@gmail.com
License: UNKNOWN
Platform: UNKNOWN
